{
    "image_wh": [
        3000,
        1857
    ],
    "rect_LTRB": [
        [
            2403,
            113,
            2891,
            1695
        ],
        [
            148,
            420,
            321,
            1147
        ],
        [
            1374,
            1270,
            1580,
            1547
        ],
        [
            1480,
            1043,
            1552,
            1115
        ],
        [
            1464,
            1168,
            1556,
            1297
        ],
        [
            307,
            388,
            403,
            502
        ],
        [
            778,
            394,
            827,
            482
        ],
        [
            944,
            391,
            1002,
            474
        ],
        [
            1005,
            414,
            1060,
            475
        ],
        [
            1073,
            398,
            1133,
            475
        ],
        [
            1233,
            376,
            1316,
            472
        ],
        [
            1431,
            378,
            1520,
            469
        ],
        [
            1676,
            368,
            1755,
            498
        ],
        [
            1787,
            366,
            1860,
            466
        ],
        [
            2045,
            378,
            2105,
            489
        ],
        [
            133,
            1156,
            2363,
            1321
        ],
        [
            278,
            447,
            2226,
            1088
        ],
        [
            133,
            300,
            2375,
            1329
        ]
    ],
    "rect_classes": [
        0,
        1,
        2,
        3,
        4,
        5,
        5,
        5,
        5,
        5,
        5,
        5,
        5,
        5,
        5,
        6,
        7,
        8
    ],
    "class_names": [
        "calibration_card",
        "initial",
        "seal",
        "filler",
        "seal_ties",
        "decorative",
        "plica",
        "old_text",
        "writable_area"
    ],
    "class_colors": [],
    "user": "",
    "image_md5": "16fad8a59b502c80f3421079797b2dca"
}