{
    "image_wh": [
        3000,
        2475
    ],
    "rect_LTRB": [
        [
            2327,
            83,
            2875,
            1850
        ],
        [
            415,
            310,
            517,
            458
        ],
        [
            1637,
            1445,
            2226,
            1502
        ],
        [
            1190,
            1558,
            1403,
            2228
        ],
        [
            194,
            1502,
            2278,
            1724
        ],
        [
            1960,
            340,
            2044,
            461
        ],
        [
            1157,
            362,
            1214,
            463
        ],
        [
            415,
            415,
            2141,
            1500
        ],
        [
            194,
            215,
            2278,
            1724
        ]
    ],
    "rect_classes": [
        0,
        1,
        2,
        3,
        4,
        5,
        5,
        6,
        7
    ],
    "class_names": [
        "calibration_card",
        "initial",
        "filler",
        "seal_ties",
        "plica",
        "decorative",
        "old_text",
        "writable_area"
    ],
    "class_colors": [],
    "user": "",
    "image_md5": "1a958b271bddb4d0cb277e2d97dd9a9e"
}