{
    "image_wh": [
        3000,
        1874
    ],
    "rect_LTRB": [
        [
            85,
            167,
            601,
            1744
        ],
        [
            855,
            120,
            1028,
            1023
        ],
        [
            1481,
            1408,
            1903,
            1829
        ],
        [
            1714,
            1022,
            1879,
            1434
        ],
        [
            1004,
            187,
            1031,
            229
        ],
        [
            1026,
            906,
            1159,
            1055
        ],
        [
            1186,
            902,
            1327,
            1054
        ],
        [
            1609,
            902,
            1672,
            1013
        ],
        [
            2392,
            923,
            2536,
            1071
        ],
        [
            2307,
            908,
            2396,
            1054
        ],
        [
            2162,
            929,
            2338,
            1044
        ],
        [
            805,
            995,
            2845,
            1153
        ],
        [
            986,
            203,
            2756,
            959
        ],
        [
            802,
            101,
            2853,
            1149
        ]
    ],
    "rect_classes": [
        0,
        1,
        2,
        3,
        4,
        4,
        4,
        4,
        4,
        4,
        4,
        5,
        6,
        7
    ],
    "class_names": [
        "calibration_card",
        "initial",
        "seal",
        "seal_ties",
        "decorative",
        "plica",
        "old_text",
        "writable_area"
    ],
    "class_colors": [],
    "user": "",
    "image_md5": "20346b362bc5cb734ca0fadba7b55efe"
}