{
    "image_wh": [
        3000,
        2135
    ],
    "rect_LTRB": [
        [
            2324,
            83,
            2919,
            2036
        ],
        [
            491,
            392,
            631,
            575
        ],
        [
            940,
            1022,
            1601,
            1191
        ],
        [
            617,
            490,
            2218,
            1010
        ],
        [
            133,
            312,
            2266,
            1802
        ]
    ],
    "rect_classes": [
        0,
        1,
        2,
        3,
        4
    ],
    "class_names": [
        "calibration_card",
        "initial",
        "old_note",
        "old_text",
        "writable_area"
    ],
    "class_colors": [],
    "user": "",
    "image_md5": "306804b4918aa4957a29ef27ba660621"
}