{
    "image_wh": [
        3000,
        1926
    ],
    "rect_LTRB": [
        [
            2339,
            78,
            2859,
            1769
        ],
        [
            445,
            369,
            571,
            490
        ],
        [
            1190,
            1310,
            1444,
            1379
        ],
        [
            1149,
            1402,
            1310,
            1849
        ],
        [
            1874,
            385,
            1940,
            492
        ],
        [
            1292,
            401,
            1330,
            502
        ],
        [
            1248,
            410,
            1286,
            489
        ],
        [
            1173,
            383,
            1226,
            487
        ],
        [
            1027,
            399,
            1091,
            480
        ],
        [
            2073,
            432,
            2111,
            507
        ],
        [
            273,
            1371,
            2270,
            1514
        ],
        [
            445,
            452,
            2224,
            1342
        ],
        [
            270,
            321,
            2294,
            1524
        ]
    ],
    "rect_classes": [
        0,
        1,
        2,
        3,
        4,
        4,
        4,
        4,
        4,
        4,
        5,
        6,
        7
    ],
    "class_names": [
        "calibration_card",
        "initial",
        "filler",
        "seal_ties",
        "decorative",
        "plica",
        "old_text",
        "writable_area"
    ],
    "class_colors": [],
    "user": "",
    "image_md5": "83b2329a4dcc138d6da0949c5d664487"
}