{
    "image_wh": [
        3000,
        1974
    ],
    "rect_LTRB": [
        [
            2298,
            82,
            2835,
            1846
        ],
        [
            352,
            580,
            547,
            1050
        ],
        [
            1988,
            1200,
            2056,
            1257
        ],
        [
            451,
            647,
            502,
            715
        ],
        [
            466,
            668,
            2072,
            1263
        ],
        [
            259,
            498,
            2155,
            1659
        ]
    ],
    "rect_classes": [
        0,
        1,
        2,
        3,
        4,
        5
    ],
    "class_names": [
        "calibration_card",
        "initial",
        "filler",
        "decorative",
        "old_text",
        "writable_area"
    ],
    "class_colors": [],
    "user": "",
    "image_md5": "a6724a95e762a953afa84329407c7999"
}