{
    "image_wh": [
        3000,
        2634
    ],
    "rect_LTRB": [
        [
            2358,
            68,
            2959,
            2001
        ],
        [
            293,
            261,
            554,
            434
        ],
        [
            1859,
            1056,
            2056,
            1104
        ],
        [
            1097,
            1188,
            1665,
            2345
        ],
        [
            526,
            354,
            588,
            438
        ],
        [
            915,
            355,
            968,
            445
        ],
        [
            1096,
            346,
            1238,
            431
        ],
        [
            1481,
            356,
            1522,
            427
        ],
        [
            1855,
            357,
            1904,
            423
        ],
        [
            1938,
            369,
            1975,
            426
        ],
        [
            1241,
            363,
            1281,
            428
        ],
        [
            181,
            1134,
            2302,
            1360
        ],
        [
            431,
            395,
            2238,
            1092
        ],
        [
            181,
            259,
            2310,
            1364
        ]
    ],
    "rect_classes": [
        0,
        1,
        2,
        3,
        4,
        4,
        4,
        4,
        4,
        4,
        4,
        5,
        6,
        7
    ],
    "class_names": [
        "calibration_card",
        "initial",
        "filler",
        "seal_ties",
        "decorative",
        "plica",
        "old_text",
        "writable_area"
    ],
    "class_colors": [],
    "user": "",
    "image_md5": "d2dd9559a15560995054dcbccb930026"
}